{
  "code": 0,
  "msg": "",
  "count": 19,
  "data": [
    {
      "authorityId": 2,
      "authorityName": "房管一所",
      "orderNumber": 2,
      "menuUrl": "system/user",
      "menuIcon": null,
      "createTime": "2018/06/29 11:05:41",
      "authority": null,
      "checked": 0,
      "updateTime": "2018/07/13 09:13:42",
      "isMenu": 0,
      "parentId": 1
    },
    {
      "authorityId": 4,
      "authorityName": "ZZZ",
      "orderNumber": 4,
      "menuUrl": null,
      "menuIcon": null,
      "createTime": "2018/06/29 11:05:41",
      "authority": "user:add",
      "checked": 0,
      "updateTime": "2018/07/13 09:13:42",
      "isMenu": 1,
      "parentId": 2
    },
    {
      "authorityId": 5,
      "authorityName": "AAA",
      "orderNumber": 5,
      "menuUrl": null,
      "menuIcon": null,
      "createTime": "2018/06/29 11:05:41",
      "authority": "user:edit",
      "checked": 0,
      "updateTime": "2018/07/13 09:13:42",
      "isMenu": 1,
      "parentId": 2
    },
    {
      "authorityId": 6,
      "authorityName": "QQQ",
      "orderNumber": 6,
      "menuUrl": null,
      "menuIcon": null,
      "createTime": "2018/06/29 11:05:41",
      "authority": "user:delete",
      "checked": 0,
      "updateTime": "2018/07/13 09:13:42",
      "isMenu": 1,
      "parentId": 2
    },
    {
      "authorityId": 7,
      "authorityName": "房管二所",
      "orderNumber": 7,
      "menuUrl": "system/role",
      "menuIcon": null,
      "createTime": "2018/06/29 11:05:41",
      "authority": null,
      "checked": 0,
      "updateTime": "2018/07/13 09:13:42",
      "isMenu": 0,
      "parentId": 1
    },
    {
      "authorityId": 8,
      "authorityName": "GGG",
      "orderNumber": 8,
      "menuUrl": "",
      "menuIcon": "",
      "createTime": "2018/07/21 13:54:59",
      "authority": "role:view",
      "checked": 0,
      "updateTime": "2018/07/21 13:54:58",
      "isMenu": 1,
      "parentId": 7
    },
    {
      "authorityId": 9,
      "authorityName": "BBB",
      "orderNumber": 9,
      "menuUrl": "",
      "menuIcon": "",
      "createTime": "2018/06/29 11:05:41",
      "authority": "role:add",
      "checked": 0,
      "updateTime": "2018/07/13 09:13:42",
      "isMenu": 1,
      "parentId": 7
    },
    {
      "authorityId": 10,
      "authorityName": "VVV",
      "orderNumber": 10,
      "menuUrl": "",
      "menuIcon": "",
      "createTime": "2018/06/29 11:05:41",
      "authority": "role:edit",
      "checked": 0,
      "updateTime": "2018/07/13 09:13:42",
      "isMenu": 1,
      "parentId": 7
    },
    {
      "authorityId": 11,
      "authorityName": "GGG",
      "orderNumber": 11,
      "menuUrl": "",
      "menuIcon": "",
      "createTime": "2018/06/29 11:05:41",
      "authority": "role:delete",
      "checked": 0,
      "updateTime": "2018/07/13 09:13:42",
      "isMenu": 1,
      "parentId": 7
    },
    {
      "authorityId": 12,
      "authorityName": "FFF",
      "orderNumber": 12,
      "menuUrl": "",
      "menuIcon": "",
      "createTime": "2018/06/29 11:05:41",
      "authority": "role:auth",
      "checked": 0,
      "updateTime": "2018/07/13 15:27:18",
      "isMenu": 1,
      "parentId": 7
    },
    {
      "authorityId": 13,
      "authorityName": "房管三所",
      "orderNumber": 13,
      "menuUrl": "system/authorities",
      "menuIcon": null,
      "createTime": "2018/06/29 11:05:41",
      "authority": null,
      "checked": 0,
      "updateTime": "2018/07/13 15:45:13",
      "isMenu": 0,
      "parentId": 1
    },
    {
      "authorityId": 14,
      "authorityName": "DDD",
      "orderNumber": 14,
      "menuUrl": "",
      "menuIcon": "",
      "createTime": "2018/07/21 13:55:57",
      "authority": "authorities:view",
      "checked": 0,
      "updateTime": "2018/07/21 13:55:56",
      "isMenu": 1,
      "parentId": 13
    },
    {
      "authorityId": 15,
      "authorityName": "CCC",
      "orderNumber": 15,
      "menuUrl": "",
      "menuIcon": "",
      "createTime": "2018/06/29 11:05:41",
      "authority": "authorities:add",
      "checked": 0,
      "updateTime": "2018/06/29 11:05:41",
      "isMenu": 1,
      "parentId": 13
    },
    {
      "authorityId": 16,
      "authorityName": "SSS",
      "orderNumber": 16,
      "menuUrl": "",
      "menuIcon": "",
      "createTime": "2018/07/13 09:13:42",
      "authority": "authorities:edit",
      "checked": 0,
      "updateTime": "2018/07/13 09:13:42",
      "isMenu": 1,
      "parentId": 13
    },
    {
      "authorityId": 17,
      "authorityName": "WWW",
      "orderNumber": 17,
      "menuUrl": "",
      "menuIcon": "",
      "createTime": "2018/06/29 11:05:41",
      "authority": "authorities:delete",
      "checked": 0,
      "updateTime": "2018/06/29 11:05:41",
      "isMenu": 1,
      "parentId": 13
    },
    {
      "authorityId": 18,
      "authorityName": "房管四所",
      "orderNumber": 18,
      "menuUrl": "system/loginRecord",
      "menuIcon": null,
      "createTime": "2018/06/29 11:05:41",
      "authority": null,
      "checked": 0,
      "updateTime": "2018/06/29 11:05:41",
      "isMenu": 0,
      "parentId": 1
    }
  ]
}